genai/__init__.py
genai/_types.py
genai/_utils/__init__.py
genai/_utils/api_client.py
genai/_utils/async_executor.py
genai/_utils/asyncio_future.py
genai/_utils/deprecated_schema_import.py
genai/_utils/general.py
genai/_utils/http_client/__init__.py
genai/_utils/http_client/httpx_client.py
genai/_utils/http_client/rate_limit_transport.py
genai/_utils/http_client/retry_transport.py
genai/_utils/limiters/adjustable_semaphor.py
genai/_utils/limiters/base_limiter.py
genai/_utils/limiters/container_limiter.py
genai/_utils/limiters/dummy_limiter.py
genai/_utils/limiters/external_limiter.py
genai/_utils/limiters/local_limiter.py
genai/_utils/limiters/shared_limiter.py
genai/_utils/queues/flushable_queue.py
genai/_utils/queues/ordered_queue.py
genai/_utils/responses.py
genai/_utils/service/__init__.py
genai/_utils/service/base_service.py
genai/_utils/service/metadata.py
genai/_utils/shared_instance.py
genai/_utils/shared_loop.py
genai/_utils/shared_options.py
genai/_utils/validators.py
genai/_version.py
genai/client.py
genai/credentials.py
genai/exceptions.py
genai/extensions/__init__.py
genai/extensions/_common/__init__.py
genai/extensions/_common/utils.py
genai/extensions/huggingface/__init__.py
genai/extensions/huggingface/agent.py
genai/extensions/langchain/__init__.py
genai/extensions/langchain/chat_llm.py
genai/extensions/langchain/embeddings.py
genai/extensions/langchain/llm.py
genai/extensions/langchain/template.py
genai/extensions/langchain/utils.py
genai/extensions/llama_index/__init__.py
genai/extensions/llama_index/embeddings.py
genai/extensions/llama_index/llm.py
genai/extensions/localserver/__init__.py
genai/extensions/localserver/local_api_server.py
genai/extensions/localserver/local_base_model.py
genai/extensions/localserver/schema.py
genai/file/__init__.py
genai/file/file_service.py
genai/model/__init__.py
genai/model/model_service.py
genai/prompt/__init__.py
genai/prompt/prompt_service.py
genai/py.typed
genai/request/__init__.py
ibm_generative_ai-2.2.0.dist-info/LICENSE
ibm_generative_ai-2.2.0.dist-info/METADATA
ibm_generative_ai-2.2.0.dist-info/WHEEL
ibm_generative_ai-2.2.0.dist-info/RECORD
