Metadata-Version: 2.1
Name: ibm-generative-ai
Version: 2.2.0
Summary: IBM Generative AI is a Python library built on IBM's large language model REST interface.
Author: Tomas Dvorak
Author-email: tomas.dvorak@ibm.com
Maintainer: Tomas Dvorak
Maintainer-email: tomas.dvorak@ibm.com
Requires-Python: >=3.9,<4.0
Classifier: Programming Language :: Python :: 3
Classifier: Programming Language :: Python :: 3.9
Classifier: Programming Language :: Python :: 3.10
Classifier: Programming Language :: Python :: 3.11
Classifier: Programming Language :: Python :: 3.12
Provides-Extra: huggingface
Provides-Extra: langchain
Provides-Extra: llama-index
Provides-Extra: localserver
Requires-Dist: aiolimiter (>=1.1.0,<2.0.0)
Requires-Dist: datasets (>=2.13.0,<3.0.0) ; extra == "huggingface"
Requires-Dist: fastapi (>=0.100.0,<0.101.0) ; extra == "localserver"
Requires-Dist: httpx (>=0.26.0,<0.27.0)
Requires-Dist: httpx-sse (>=0.3.0,<0.4.0)
Requires-Dist: langchain-core (>=0.1.0,<0.2.0) ; extra == "langchain"
Requires-Dist: llama-index (>=0.9.15,<0.10.0) ; extra == "llama-index"
Requires-Dist: pydantic (>=2.0.0,<3.0.0)
Requires-Dist: pyyaml (>=6.0.0,<7.0.0) ; extra == "langchain"
Requires-Dist: transformers[agents] (>=4.33.3,<5.0.0) ; extra == "huggingface"
Requires-Dist: uvicorn (>=0.22.0,<0.23.0) ; extra == "localserver"
